pyassist/CustomError.py
pyassist/__init__.py
pyassist/process.py
pyassist/utils.py
pyassist/Network/__init__.py
pyassist/Network/network.py
pyassist/Network/proxy.py
pyassist/Scraper/__init__.py
pyassist/Scraper/bs4.py
pyassist/Scraper/selenium.py
pyassist-0.2.4.dist-info/LICENSE
pyassist-0.2.4.dist-info/METADATA
pyassist-0.2.4.dist-info/WHEEL
pyassist-0.2.4.dist-info/top_level.txt
pyassist-0.2.4.dist-info/RECORD
