Metadata-Version: 2.1
Name: pyassist
Version: 0.2.4
Summary: This is Python Utility
Home-page: https://github.com/ISabariRajan
Download-URL: https://github.com/ISabariRajan/Utilities/archive/refs/tags/v-0.2.4.tar.gz
Author: Sabari Rajan
Author-email: mailme@isbarirajan.com
License: MIT
Keywords: Utility,utils,pyutils,assist,easy,service
Classifier: Development Status :: 3 - Alpha
Classifier: Intended Audience :: Developers
Classifier: Topic :: Software Development :: Build Tools
Classifier: License :: OSI Approved :: MIT License
Classifier: Programming Language :: Python :: 3
Classifier: Programming Language :: Python :: 3.4
Classifier: Programming Language :: Python :: 3.5
Classifier: Programming Language :: Python :: 3.6
License-File: LICENSE
Requires-Dist: lxml
Requires-Dist: pyloggerutils
Requires-Dist: requests
Requires-Dist: urllib3
Requires-Dist: BeautifulSoup4
Requires-Dist: webdriver-manager
Requires-Dist: selenium
